pynecone_supporter/__init__.py
pynecone_supporter/components/__init__.py
pynecone_supporter/components/color_picker.py
pynecone_supporter/components/json_editor.py
pynecone_supporter/components/jumo_button.py
pynecone_supporter/components/webcam.py
pynecone_supporter-0.0.6.dist-info/METADATA
pynecone_supporter-0.0.6.dist-info/WHEEL
pynecone_supporter-0.0.6.dist-info/top_level.txt
pynecone_supporter-0.0.6.dist-info/RECORD
