Metadata-Version: 2.1
Name: pynecone-supporter
Version: 0.0.6
Summary: Pynecone supporter
Home-page: https://github.com/automatethem/pynecone-supporter
Author: Sang Ki Kwon
Author-email: automatethem@gmail.com
License: MIT
Requires-Dist: pynecone
